Workbook

Sheet Dashboard
A1: RETAIL SALES PERFORMANCE DASHBOARD
A3: Dataset: 300 sample retail orders | Period: Jan 2024 – Dec 2025
A5: TOTAL REVENUE | D5: TOTAL PROFIT | G5: TOTAL ORDERS | J5: UNITS SOLD | M5: PROFIT MARGIN
A6: =Analysis!L4 | D6: =Analysis!L5 | G6: =Analysis!L6 | J6: =Analysis!L7 | M6: =Analysis!L8
A9: Interactive category filter: | C9: All Categories | E9: Selected category revenue: | G9: =IF(C9="All Categories",Analysis!L4,SUMIF('Raw Data'!$D$2:$D$301,C9,'Raw Data'!$J$2:$J$301))
A27: KEY INSIGHTS
A28: 1. Use the category dropdown to view revenue for a selected category.
A29: 2. Monthly trend chart helps identify stronger and weaker sales periods.
A30: 3. Regional pie chart compares each region's contribution to revenue.
A31: 4. Revenue and profit KPIs summarize overall performance.
A33: Note: This workbook uses an illustrative sample dataset for demonstration. If your examiner requires a downloaded Kaggle/UCI dataset, replace the Raw Data sheet with that dataset and update the formulas/ranges.

Sheet Raw Data
A1: Order ID | B1: Order Date | C1: Product | D1: Category | E1: Region | F1: Sales Channel | G1: Quantity | H1: Unit Price (₹) | I1: Discount | J1: Revenue (₹) | K1: Cost (₹) | L1: Profit (₹)
A2: ORD0085 | B2: 45294 | C2: Wallet | D2: Fashion | E2: South | F2: Wholesale | G2: 8 | H2: 713.96 | I2: 0 | J2: 5711.68 | K2: 3397.92 | L2: 2313.76
A3: ORD0224 | B3: 45301 | C3: Notebook Pack | D3: Stationery | E3: North | F3: Wholesale | G3: 6 | H3: 237.4 | I3: 0.15 | J3: 1210.74 | K3: 794.64 | L3: 416.1
A4: ORD0074 | B4: 45302 | C4: Water Bottle | D4: Home & Kitchen | E4: North | F4: Wholesale | G4: 4 | H4: 495.91 | I4: 0.1 | J4: 1785.28 | K4: 1186.04 | L4: 599.24
A5: ORD0213 | B5: 45311 | C5: Cap | D5: Fashion | E5: East | F5: Wholesale | G5: 7 | H5: 316.05 | I5: 0 | J5: 2212.35 | K5: 1386.48 | L5: 825.87
A6: ORD0191 | B6: 45318 | C6: Planner | D6: Stationery | E6: West | F6: Online | G6: 8 | H6: 395.95 | I6: 0.15 | J6: 2692.46 | K6: 1490.92 | L6: 1201.54
A7: ORD0273 | B7: 45318 | C7: Mouse | D7: Electronics | E7: West | F7: Store | G7: 2 | H7: 741.25 | I7: 0.05 | J7: 1408.38 | K7: 1048.63 | L7: 359.75
A8: ORD0096 | B8: 45321 | C8: Lunch Box | D8: Home & Kitchen | E8: North | F8: Online | G8: 5 | H8: 677.82 | I8: 0.15 | J8: 2880.74 | K8: 1803.57 | L8: 1077.17
A9: ORD0269 | B9: 45322 | C9: Markers | D9: Stationery | E9: East | F9: Online | G9: 8 | H9: 204.57 | I9: 0.15 | J9: 1391.08 | K9: 1063.75 | L9: 327.33
A10: ORD0299 | B10: 45325 | C10: Pens Set | D10: Stationery | E10: East | F10: Wholesale | G10: 5 | H10: 163.6 | I10: 0.1 | J10: 736.2 | K10: 491.1 | L10: 245.1
A11: ORD0065 | B11: 45333 | C11: Keyboard | D11: Electronics | E11: North | F11: Store | G11: 4 | H11: 2058.71 | I11: 0.15 | J11: 6999.61 | K11: 3917.12 | L11: 3082.49
A12: ORD0197 | B12: 45334 | C12: Headphones | D12: Electronics | E12: North | F12: Wholesale | G12: 1 | H12: 1418.39 | I12: 0.15 | J12: 1205.63 | K12: 709.89 | L12: 495.74
A13: ORD0218 | B13: 45335 | C13: Notebook Pack | D13: Stationery | E13: North | F13: Online | G13: 6 | H13: 293.35 | I13: 0.05 | J13: 1672.1 | K13: 1194.39 | L13: 477.71
... A301: ORD0271 | B301: 46020 | C301: Storage Box | D301: Home & Kitchen | E301: South | F301: Store | G301: 6 | H301: 781 | I301: 0 | J301: 4686 | K301: 2443.05 | L301: 2242.95

Sheet Analysis
A1: SALES DASHBOARD — ANALYSIS
A3: Monthly Revenue | E3: Revenue by Category | H3: Revenue by Region | K3: KPI | L3: Value
A4: Month | B4: Revenue (₹) | C4: Profit (₹) | E4: Category | F4: Revenue (₹) | H4: Region | I4: Revenue (₹) | K4: Total Revenue | L4: =SUM('Raw Data'!$J$2:$J$301)
A5: 45292 | B5: =SUMIFS('Raw Data'!$J$2:$J$301,'Raw Data'!$B$2:$B$301,">="&A5,'Raw Data'!$B$2:$B$301,"<"&EDATE(A5,1)) | C5: =SUMIFS('Raw Data'!$L$2:$L$301,'Raw Data'!$B$2:$B$301,">="&A5,'Raw Data'!$B$2:$B$301,"<"&EDATE(A5,1)) | E5: Electronics | F5: =SUMIF('Raw Data'!$D$2:$D$301,E5,'Raw Data'!$J$2:$J$301) | H5: West | I5: =SUMIF('Raw Data'!$E$2:$E$301,H5,'Raw Data'!$J$2:$J$301) | K5: Total Profit | L5: =SUM('Raw Data'!$L$2:$L$301)
A6: 45323 | B6: =SUMIFS('Raw Data'!$J$2:$J$301,'Raw Data'!$B$2:$B$301,">="&A6,'Raw Data'!$B$2:$B$301,"<"&EDATE(A6,1)) | C6: =SUMIFS('Raw Data'!$L$2:$L$301,'Raw Data'!$B$2:$B$301,">="&A6,'Raw Data'!$B$2:$B$301,"<"&EDATE(A6,1)) | E6: Home & Kitchen | F6: =SUMIF('Raw Data'!$D$2:$D$301,E6,'Raw Data'!$J$2:$J$301) | H6: North | I6: =SUMIF('Raw Data'!$E$2:$E$301,H6,'Raw Data'!$J$2:$J$301) | K6: Orders | L6: =COUNTA('Raw Data'!$A$2:$A$301)
A7: 45352 | B7: =SUMIFS('Raw Data'!$J$2:$J$301,'Raw Data'!$B$2:$B$301,">="&A7,'Raw Data'!$B$2:$B$301,"<"&EDATE(A7,1)) | C7: =SUMIFS('Raw Data'!$L$2:$L$301,'Raw Data'!$B$2:$B$301,">="&A7,'Raw Data'!$B$2:$B$301,"<"&EDATE(A7,1)) | E7: Stationery | F7: =SUMIF('Raw Data'!$D$2:$D$301,E7,'Raw Data'!$J$2:$J$301) | H7: South | I7: =SUMIF('Raw Data'!$E$2:$E$301,H7,'Raw Data'!$J$2:$J$301) | K7: Units Sold | L7: =SUM('Raw Data'!$G$2:$G$301)
A8: 45383 | B8: =SUMIFS('Raw Data'!$J$2:$J$301,'Raw Data'!$B$2:$B$301,">="&A8,'Raw Data'!$B$2:$B$301,"<"&EDATE(A8,1)) | C8: =SUMIFS('Raw Data'!$L$2:$L$301,'Raw Data'!$B$2:$B$301,">="&A8,'Raw Data'!$B$2:$B$301,"<"&EDATE(A8,1)) | E8: Fashion | F8: =SUMIF('Raw Data'!$D$2:$D$301,E8,'Raw Data'!$J$2:$J$301) | H8: East | I8: =SUMIF('Raw Data'!$E$2:$E$301,H8,'Raw Data'!$J$2:$J$301) | K8: Profit Margin | L8: =IFERROR(L5/L4,0)
A9: 45413 | B9: =SUMIFS('Raw Data'!$J$2:$J$301,'Raw Data'!$B$2:$B$301,">="&A9,'Raw Data'!$B$2:$B$301,"<"&EDATE(A9,1)) | C9: =SUMIFS('Raw Data'!$L$2:$L$301,'Raw Data'!$B$2:$B$301,">="&A9,'Raw Data'!$B$2:$B$301,"<"&EDATE(A9,1))
A10: 45444 | B10: =SUMIFS('Raw Data'!$J$2:$J$301,'Raw Data'!$B$2:$B$301,">="&A10,'Raw Data'!$B$2:$B$301,"<"&EDATE(A10,1)) | C10: =SUMIFS('Raw Data'!$L$2:$L$301,'Raw Data'!$B$2:$B$301,">="&A10,'Raw Data'!$B$2:$B$301,"<"&EDATE(A10,1))
A11: 45474 | B11: =SUMIFS('Raw Data'!$J$2:$J$301,'Raw Data'!$B$2:$B$301,">="&A11,'Raw Data'!$B$2:$B$301,"<"&EDATE(A11,1)) | C11: =SUMIFS('Raw Data'!$L$2:$L$301,'Raw Data'!$B$2:$B$301,">="&A11,'Raw Data'!$B$2:$B$301,"<"&EDATE(A11,1))
A12: 45505 | B12: =SUMIFS('Raw Data'!$J$2:$J$301,'Raw Data'!$B$2:$B$301,">="&A12,'Raw Data'!$B$2:$B$301,"<"&EDATE(A12,1)) | C12: =SUMIFS('Raw Data'!$L$2:$L$301,'Raw Data'!$B$2:$B$301,">="&A12,'Raw Data'!$B$2:$B$301,"<"&EDATE(A12,1))
A13: 45536 | B13: =SUMIFS('Raw Data'!$J$2:$J$301,'Raw Data'!$B$2:$B$301,">="&A13,'Raw Data'!$B$2:$B$301,"<"&EDATE(A13,1)) | C13: =SUMIFS('Raw Data'!$L$2:$L$301,'Raw Data'!$B$2:$B$301,">="&A13,'Raw Data'!$B$2:$B$301,"<"&EDATE(A13,1))
A14: 45566 | B14: =SUMIFS('Raw Data'!$J$2:$J$301,'Raw Data'!$B$2:$B$301,">="&A14,'Raw Data'!$B$2:$B$301,"<"&EDATE(A14,1)) | C14: =SUMIFS('Raw Data'!$L$2:$L$301,'Raw Data'!$B$2:$B$301,">="&A14,'Raw Data'!$B$2:$B$301,"<"&EDATE(A14,1))
A15: 45597 | B15: =SUMIFS('Raw Data'!$J$2:$J$301,'Raw Data'!$B$2:$B$301,">="&A15,'Raw Data'!$B$2:$B$301,"<"&EDATE(A15,1)) | C15: =SUMIFS('Raw Data'!$L$2:$L$301,'Raw Data'!$B$2:$B$301,">="&A15,'Raw Data'!$B$2:$B$301,"<"&EDATE(A15,1))
A16: 45627 | B16: =SUMIFS('Raw Data'!$J$2:$J$301,'Raw Data'!$B$2:$B$301,">="&A16,'Raw Data'!$B$2:$B$301,"<"&EDATE(A16,1)) | C16: =SUMIFS('Raw Data'!$L$2:$L$301,'Raw Data'!$B$2:$B$301,">="&A16,'Raw Data'!$B$2:$B$301,"<"&EDATE(A16,1))
A17: 45658 | B17: =SUMIFS('Raw Data'!$J$2:$J$301,'Raw Data'!$B$2:$B$301,">="&A17,'Raw Data'!$B$2:$B$301,"<"&EDATE(A17,1)) | C17: =SUMIFS('Raw Data'!$L$2:$L$301,'Raw Data'!$B$2:$B$301,">="&A17,'Raw Data'!$B$2:$B$301,"<"&EDATE(A17,1))
A18: 45689 | B18: =SUMIFS('Raw Data'!$J$2:$J$301,'Raw Data'!$B$2:$B$301,">="&A18,'Raw Data'!$B$2:$B$301,"<"&EDATE(A18,1)) | C18: =SUMIFS('Raw Data'!$L$2:$L$301,'Raw Data'!$B$2:$B$301,">="&A18,'Raw Data'!$B$2:$B$301,"<"&EDATE(A18,1))
A19: 45717 | B19: =SUMIFS('Raw Data'!$J$2:$J$301,'Raw Data'!$B$2:$B$301,">="&A19,'Raw Data'!$B$2:$B$301,"<"&EDATE(A19,1)) | C19: =SUMIFS('Raw Data'!$L$2:$L$301,'Raw Data'!$B$2:$B$301,">="&A19,'Raw Data'!$B$2:$B$301,"<"&EDATE(A19,1))
A20: 45748 | B20: =SUMIFS('Raw Data'!$J$2:$J$301,'Raw Data'!$B$2:$B$301,">="&A20,'Raw Data'!$B$2:$B$301,"<"&EDATE(A20,1)) | C20: =SUMIFS('Raw Data'!$L$2:$L$301,'Raw Data'!$B$2:$B$301,">="&A20,'Raw Data'!$B$2:$B$301,"<"&EDATE(A20,1))
... A28: 45992 | B28: =SUMIFS('Raw Data'!$J$2:$J$301,'Raw Data'!$B$2:$B$301,">="&A28,'Raw Data'!$B$2:$B$301,"<"&EDATE(A28,1)) | C28: =SUMIFS('Raw Data'!$L$2:$L$301,'Raw Data'!$B$2:$B$301,">="&A28,'Raw Data'!$B$2:$B$301,"<"&EDATE(A28,1))

Sheet Project Guide
A1: PROJECT GUIDE: RETAIL SALES DASHBOARD
A2: Project objective | B2: Analyze retail sales, profit, product categories, regions, and monthly trends in Excel.
A3: Workbook sheets | B3: Dashboard: KPI cards and charts | Raw Data: 300 sample orders | Analysis: formula-driven summaries | Project Guide: instructions.
A4: How to use the filter | B4: On Dashboard, select a category from cell C9. The selected category revenue KPI updates automatically.
A5: Formulas included | B5: SUM, SUMIF, SUMIFS, COUNTA, IFERROR, EDATE. Formulas are visible in the Analysis sheet.
A6: Charts included | B6: Column/bar chart: revenue by category | Line chart: monthly revenue trend | Pie chart: revenue share by region.
A7: How to update data | B7: Paste new records into Raw Data using the same columns. If row count changes, extend formula ranges in Analysis.
A8: Dataset note | B8: The included 300-row dataset is illustrative/simulated for demonstrating dashboard features; it is not represented as an original Kaggle/UCI download.
A9: Possible public source | B9: UCI Online Retail dataset: https://archive.ics.uci.edu/dataset/352/online+retail. Use the original dataset if your exam requires a dataset downloaded from UCI/Kaggle.
A10: Suggested submission name | B10: Harsh_ExcelDashboard.xlsx
